{
	"pages": [ //pages数组中第一项表示应用启动页，参考：https://uniapp.dcloud.io/collocation/pages
		{
			"path": "pages/index/index",
			"style": {
				"navigationBarTitleText": "首页"
			}
		},
		{
			"path": "pages/index/wealth",
			"style": {
				"navigationBarTitleText": "财富"
			}
		},
		{
			"path": "pages/index/friend",
			"style": {
				"navigationBarTitleText": "朋友"
			}
		},
		{
			"path": "pages/index/ucenter",
			"style": {
				"navigationBarTitleText": "我的"
			}
		}
	],
	"tabBar": {
		"color": "#000000",
		"selectedColor": "#1a81d0",
		"backgroundColor": "#fafbff",
		"borderStyle": "black",
		"list": [{
				"pagePath": "pages/index/index",
				"iconPath": "static/home.png",
				"selectedIconPath": "static/home-active.png",
				"text": "首页"
			},
			{
				"pagePath": "pages/index/wealth",
				"iconPath": "static/money.png",
				"selectedIconPath": "static/money-active.png",
				"text": "财富"
			},
			{
				"pagePath": "pages/index/friend",
				"iconPath": "static/shejiao1.png",
				"selectedIconPath": "static/shejiao2.png",
				"text": "朋友"
			},
			{
				"pagePath": "pages/index/ucenter",
				"iconPath": "static/center.png",
				"selectedIconPath": "static/center-active.png",
				"text": "我的"
			}
		]

	},
	"globalStyle": {
		"navigationBarTextStyle": "black",
		"navigationBarTitleText": "uni-app",
		"navigationBarBackgroundColor": "#F8F8F8",
		"backgroundColor": "#F8F8F8",
		"navigationStyle": "custom"
	}
}
